LICENSE
README.md
setup.cfg
setup.py
netscorpion/__init__.py
netscorpion/warnings.py
netscorpion.egg-info/PKG-INFO
netscorpion.egg-info/SOURCES.txt
netscorpion.egg-info/dependency_links.txt
netscorpion.egg-info/requires.txt
netscorpion.egg-info/top_level.txt
netscorpion/scanning/__init__.py
netscorpion/scanning/async_port_scanning.py
netscorpion/scanning/portscanning.py